{
  "sections": {
    "ce85c669-276b-4afa-a0c1-6237ec717630": {
      "type": "image-banner",
      "disabled": true,
      "blocks": {
        "template--18729374253358__ce85c669-276b-4afa-a0c1-6237ec717630-1683538762e9228075-0": {
          "type": "heading",
          "settings": {
            "heading": "Image banner",
            "heading_size": "h1"
          }
        },
        "template--18729374253358__ce85c669-276b-4afa-a0c1-6237ec717630-1683538762e9228075-1": {
          "type": "text",
          "settings": {
            "text": "Give customers details about the banner image(s) or content on the template.",
            "text_style": "body"
          }
        },
        "template--18729374253358__ce85c669-276b-4afa-a0c1-6237ec717630-1683538762e9228075-2": {
          "type": "buttons",
          "disabled": true,
          "settings": {
            "button_label_1": "Button label",
            "button_link_1": "",
            "button_style_secondary_1": false,
            "button_label_2": "Button label",
            "button_link_2": "",
            "button_style_secondary_2": false
          }
        }
      },
      "block_order": [
        "template--18729374253358__ce85c669-276b-4afa-a0c1-6237ec717630-1683538762e9228075-0",
        "template--18729374253358__ce85c669-276b-4afa-a0c1-6237ec717630-1683538762e9228075-1",
        "template--18729374253358__ce85c669-276b-4afa-a0c1-6237ec717630-1683538762e9228075-2"
      ],
      "settings": {
        "image_overlay_opacity": 0,
        "image_height": "medium",
        "desktop_content_position": "middle-center",
        "show_text_box": true,
        "desktop_content_alignment": "center",
        "color_scheme": "background-1",
        "image_behavior": "none",
        "mobile_content_alignment": "center",
        "stack_images_on_mobile": true,
        "show_text_below": true
      }
    },
    "banner": {
      "type": "main-collection-banner",
      "settings": {
        "show_collection_description": true,
        "show_collection_image": true,
        "color_scheme": "background-1"
      }
    },
    "product-grid": {
      "type": "main-collection-product-grid",
      "settings": {
        "products_per_page": 24,
        "columns_desktop": 3,
        "image_ratio": "square",
        "show_secondary_image": true,
        "show_vendor": false,
        "show_rating": true,
        "enable_quick_add": false,
        "enable_filtering": false,
        "filter_type": "horizontal",
        "enable_sorting": false,
        "columns_mobile": "2",
        "padding_top": 36,
        "padding_bottom": 36
      }
    }
  },
  "order": [
    "ce85c669-276b-4afa-a0c1-6237ec717630",
    "banner",
    "product-grid"
  ]
}
