{
  "sections": {
    "4e18b42c-dd1e-4b83-a542-21b531f9c2dd": {
      "type": "image-banner",
      "blocks": {
        "template--19044730732846__4e18b42c-dd1e-4b83-a542-21b531f9c2dd-1683538762e9228075-0": {
          "type": "heading",
          "settings": {
            "heading": "Image banner",
            "heading_size": "h1"
          }
        },
        "template--19044730732846__4e18b42c-dd1e-4b83-a542-21b531f9c2dd-1683538762e9228075-1": {
          "type": "text",
          "settings": {
            "text": "Give customers details about the banner image(s) or content on the template.",
            "text_style": "body"
          }
        },
        "template--19044730732846__4e18b42c-dd1e-4b83-a542-21b531f9c2dd-1683538762e9228075-2": {
          "type": "buttons",
          "disabled": true,
          "settings": {
            "button_label_1": "Button label",
            "button_link_1": "",
            "button_style_secondary_1": false,
            "button_label_2": "Button label",
            "button_link_2": "",
            "button_style_secondary_2": false
          }
        }
      },
      "block_order": [
        "template--19044730732846__4e18b42c-dd1e-4b83-a542-21b531f9c2dd-1683538762e9228075-0",
        "template--19044730732846__4e18b42c-dd1e-4b83-a542-21b531f9c2dd-1683538762e9228075-1",
        "template--19044730732846__4e18b42c-dd1e-4b83-a542-21b531f9c2dd-1683538762e9228075-2"
      ],
      "settings": {
        "image_overlay_opacity": 0,
        "image_height": "medium",
        "desktop_content_position": "middle-center",
        "show_text_box": true,
        "desktop_content_alignment": "center",
        "color_scheme": "background-1",
        "image_behavior": "none",
        "mobile_content_alignment": "center",
        "stack_images_on_mobile": true,
        "show_text_below": true
      }
    },
    "main": {
      "type": "main-page",
      "disabled": true,
      "settings": {
        "padding_top": 28,
        "padding_bottom": 28
      }
    },
    "8610b1f6-abc1-4844-9c8c-0f620a92f88f": {
      "type": "custom-liquid",
      "settings": {
        "custom_liquid": "<iframe src=\"https:\/\/docs.google.com\/forms\/d\/e\/1FAIpQLSff8waPslD75n8uCRhoNMtqtIVXXmUetWUGIYSSuE18qm-_4w\/viewform?embedded=true\" width=\"640\" height=\"5192\" frameborder=\"0\" marginheight=\"0\" marginwidth=\"0\">Loading…<\/iframe>",
        "color_scheme": "background-1",
        "padding_top": 40,
        "padding_bottom": 52
      }
    }
  },
  "order": [
    "4e18b42c-dd1e-4b83-a542-21b531f9c2dd",
    "main",
    "8610b1f6-abc1-4844-9c8c-0f620a92f88f"
  ]
}
